pyromongo/__init__.py
pyromongo-0.0.9.dist-info/LICENSE
pyromongo-0.0.9.dist-info/METADATA
pyromongo-0.0.9.dist-info/WHEEL
pyromongo-0.0.9.dist-info/top_level.txt
pyromongo-0.0.9.dist-info/RECORD
