Metadata-Version: 2.1
Name: pyromongo
Version: 0.0.9
Summary: Mongo Session Storage for pyrogram
Home-page: https://github.com/animeshxd/pyromongo
Author: Animesh Murmu
Author-email: am2646374@gmail.com
License: MIT
Keywords: async mongo session storage pyrogram
Classifier: Intended Audience :: Developers
Classifier: Programming Language :: Python :: 3
Classifier: Programming Language :: Python :: 3.7
Classifier: Programming Language :: Python :: 3.8
Classifier: Programming Language :: Python :: 3.9
Classifier: Programming Language :: Python :: 3.10
Classifier: Programming Language :: Python :: 3.11
Classifier: Operating System :: MacOS :: MacOS X
Classifier: Operating System :: Unix
Classifier: Operating System :: Microsoft :: Windows
Classifier: Programming Language :: Python
Requires-Python: >=3.7.0
License-File: LICENSE
Requires-Dist: motor
Requires-Dist: pymongo
Requires-Dist: Pyrogram
Provides-Extra: aws
Requires-Dist: motor[aws] ; extra == 'aws'
Provides-Extra: encryption
Requires-Dist: motor[encryption] ; extra == 'encryption'
Provides-Extra: gssapi
Requires-Dist: motor[gssapi] ; extra == 'gssapi'
Provides-Extra: ocsp
Requires-Dist: motor[ocsp] ; extra == 'ocsp'
Provides-Extra: snappy
Requires-Dist: motor[snappy] ; extra == 'snappy'
Provides-Extra: srv
Requires-Dist: motor[srv] ; extra == 'srv'
Provides-Extra: zstd
Requires-Dist: motor[zstd] ; extra == 'zstd'
